maingopy/__init__.py
maingopy/_maingopy.cp312-win_amd64.pyd
maingopy/melonpy.cp312-win_amd64.pyd
maingopy/include/tinyxml2.h
maingopy/lib/cmake/tinyxml2/tinyxml2-config-version.cmake
maingopy/lib/cmake/tinyxml2/tinyxml2-config.cmake
maingopy/lib/cmake/tinyxml2/tinyxml2-static-targets-release.cmake
maingopy/lib/cmake/tinyxml2/tinyxml2-static-targets.cmake
maingopy/lib/pkgconfig/tinyxml2.pc
maingopy-0.9.1.dist-info/licenses/AUTHORS
maingopy-0.9.1.dist-info/licenses/LICENSE
maingopy-0.9.1.dist-info/METADATA
maingopy-0.9.1.dist-info/WHEEL
maingopy-0.9.1.dist-info/top_level.txt
maingopy-0.9.1.dist-info/RECORD
