Metadata-Version: 2.4
Name: maingopy
Version: 0.9.1
Summary: A Python package for using MAiNGO - McCormick-based Algorithm for mixed-integer Nonlinear Global Optimization
Home-page: http://permalink.avt.rwth-aachen.de/?id=729717
Author: Dominik Bongartz, Jaromil Najman, Susanne Sass, Clara Witte, Alexander Mitsos
Author-email: MAiNGO@avt.rwth-aachen.de
License: EPL-2.0
Project-URL: Source, https://git.rwth-aachen.de/avt-svt/public/maingo
Project-URL: Tracker, https://git.rwth-aachen.de/avt-svt/public/maingo/-/issues
Project-URL: Documentation, https://avt-svt.pages.rwth-aachen.de/public/maingo
Keywords: optimization,global,nonlinear programming,mixed integer,NLP,MINLP,MAiNGO
Classifier: Development Status :: 4 - Beta
Classifier: Intended Audience :: Science/Research
Classifier: Topic :: Scientific/Engineering
Classifier: License :: OSI Approved :: Eclipse Public License 2.0 (EPL-2.0)
Classifier: Programming Language :: C++
Classifier: Programming Language :: Python :: 3.8
Classifier: Programming Language :: Python :: 3.9
Classifier: Programming Language :: Python :: 3.10
Classifier: Programming Language :: Python :: 3.11
Classifier: Programming Language :: Python :: 3.12
Classifier: Programming Language :: Python :: 3.13
Classifier: Operating System :: Microsoft :: Windows
Classifier: Operating System :: POSIX :: Linux
Classifier: Operating System :: MacOS :: MacOS X
License-File: LICENSE
License-File: AUTHORS
Dynamic: author
Dynamic: author-email
Dynamic: classifier
Dynamic: description
Dynamic: description-content-type
Dynamic: home-page
Dynamic: keywords
Dynamic: license
Dynamic: license-file
Dynamic: project-url
Dynamic: summary
